lighting_paperwork/channel_hookup.py
lighting_paperwork/color_cut_list.py
lighting_paperwork/excel_formatter.py
lighting_paperwork/generate_paperwork.py
lighting_paperwork/gobo_pull.py
lighting_paperwork/helpers.py
lighting_paperwork/instrument_schedule.py
lighting_paperwork/paperwork.py
lighting_paperwork/style.py
lighting_paperwork/vectorworks_xml.py
lighting_paperwork/templates/header_footer.tpl
lighting_paperwork-0.1.4.dist-info/licenses/LICENSE
lighting_paperwork-0.1.4.dist-info/METADATA
lighting_paperwork-0.1.4.dist-info/WHEEL
lighting_paperwork-0.1.4.dist-info/entry_points.txt
lighting_paperwork-0.1.4.dist-info/top_level.txt
lighting_paperwork-0.1.4.dist-info/RECORD
