Metadata-Version: 2.4
Name: lighting_paperwork
Version: 0.1.4
Summary: Generate lighting paperwork from Vectorworks XML
Author-email: Reid Sox-Harris <reid@soxharris.com>
License-Expression: GPL-3.0-only
Project-URL: repository, https://github.com/eosti/lighting-paperwork
Requires-Python: >=3.11
License-File: LICENSE
Requires-Dist: jinja2>=3.1.6
Requires-Dist: natsort>=8.4.0
Requires-Dist: numpy>=2.2.6
Requires-Dist: openpyxl>=3.1.5
Requires-Dist: pandas>=2.3.1
Requires-Dist: rich>=14.1.0
Requires-Dist: weasyprint>=66
Dynamic: license-file
